{"1001": {"name": "Choco Cake", "qn": 32, "pr": 100}, "1002": {"name": "Milk Cake", "pr": 800, "qn": 100}, "1003": {"name": "Drink", "pr": 85, "qn": 100}, "1004": {"name": "Candy", "pr": 5, "qn": 1000}, "1005": {"name": "Pen", "pr": 20, "qn": 100}, "1006": {"name": "Phone", "pr": 50000, "qn": 10}, "1007": {"name": "Game", "pr": 2999, "qn": 2}, "1008": {"name": "Case", "pr": 599, "qn": 5}, "1009": {"name": "Keyboard", "pr": 1999, "qn": 10}, "1010": {"name": "cycle", "pr": 1999, "qn": 5}, "1011": {"name": "pen", "pr": 1999, "qn": 8}, "1012": {"name": "book", "pr": 19949, "qn": 101}, "1013": {"name": "bag", "pr": 999, "qn": 14}, "1014": {"name": "pencil", "pr": 1999, "qn": 15}, "1015": {"name": "car", "pr": 19969, "qn": 120}, "1016": {"name": "Keyboard", "pr": 99, "qn": 34}, "1017": {"name": "torch", "pr": 1999, "qn": 17}, "1018": {"name": "cream", "pr": 195699, "qn": 130}, "1019": {"name": "Keyboard", "pr": 1799, "qn": 56}, "1020": {"name": "fish", "pr": 19, "qn": 40}, "1021": {"name": "cup", "pr": 19449, "qn": 1}, "1022": {"name": "shoes", "pr": 1999, "qn": 12}, "1023": {"name": "ipod", "pr": 1969, "qn": 60}, "1024": {"name": "Keyboard", "pr": 1969, "qn": 137}, "1025": {"name": "cream", "pr": 1999, "qn": 141}, "1026": {"name": "psp", "pr": 1999, "qn": 70}, "1027": {"name": "Keyboard", "pr": 199, "qn": 13}, "1028": {"name": "mobile", "pr": 1999, "qn": 120}, "1029": {"name": "bike", "pr": 1999, "qn": 329}, "1030": {"name": "camera", "pr": 1959, "qn": 2}, "1031": {"name": "doremon", "pr": 1000000, "qn": 1}}